pywipe/__init__.py
pywipe/backup.py
pywipe/config.py
pywipe/core.py
pywipe/pywipe_cli.py
pywipe/utils.py
pywipe-1.1.0.dist-info/METADATA
pywipe-1.1.0.dist-info/WHEEL
pywipe-1.1.0.dist-info/entry_points.txt
pywipe-1.1.0.dist-info/top_level.txt
pywipe-1.1.0.dist-info/RECORD
