Metadata-Version: 2.4
Name: pywipe
Version: 1.1.0
Summary: A command-line tool to reset your global Python environment.
Author-email: LMLK-seal <Yaniv.schwartz1@gmail.com>
Classifier: Programming Language :: Python :: 3
Classifier: License :: OSI Approved :: MIT License
Classifier: Operating System :: OS Independent
Requires-Python: >=3.7
Requires-Dist: click>=8.0
Requires-Dist: rich>=12.0
